cvss/__init__.py
cvss/constants2.py
cvss/constants3.py
cvss/constants4.py
cvss/cvss2.py
cvss/cvss3.py
cvss/cvss4.py
cvss/cvss_calculator.py
cvss/exceptions.py
cvss/interactive.py
cvss/parser.py
cvss-3.3.dist-info/LICENSE
cvss-3.3.dist-info/METADATA
cvss-3.3.dist-info/WHEEL
cvss-3.3.dist-info/entry_points.txt
cvss-3.3.dist-info/top_level.txt
cvss-3.3.dist-info/RECORD
