Metadata-Version: 2.1
Name: cvss
Version: 3.3
Summary: CVSS2/3/4 library with interactive calculator for Python 2 and Python 3
Home-page: https://github.com/RedHatProductSecurity/cvss
Author: Stanislav Kontar, Red Hat Product Security
Author-email: skontar@redhat.com
License: LGPLv3+
Project-URL: Releases, https://github.com/RedHatProductSecurity/cvss/releases
Project-URL: Source code, https://github.com/RedHatProductSecurity/cvss
Project-URL: Issues, https://github.com/RedHatProductSecurity/cvss/issues
Project-URL: CI, https://github.com/RedHatProductSecurity/cvss/actions
Keywords: security cvss score calculator
Classifier: Development Status :: 5 - Production/Stable
Classifier: Intended Audience :: Developers
Classifier: Topic :: Security
Classifier: License :: OSI Approved :: GNU Lesser General Public License v3 or later (LGPLv3+)
Classifier: Programming Language :: Python :: 2
Classifier: Programming Language :: Python :: 2.7
Classifier: Programming Language :: Python :: 3
Classifier: Programming Language :: Python :: 3.6
Classifier: Programming Language :: Python :: 3.7
Classifier: Programming Language :: Python :: 3.8
Classifier: Programming Language :: Python :: 3.9
Classifier: Programming Language :: Python :: 3.10
Classifier: Programming Language :: Python :: 3.11
License-File: LICENSE
